<?xml version="1.0" encoding="utf-8"?>
<TextureAtlas imagePath="ghandi.png">
	<!-- Created with Adobe Animate version 21.0.5.40714 -->
	<!-- http://www.adobe.com/products/animate.html -->
	<SubTexture name="down0000" x="5" y="5" width="293" height="102" frameX="0" frameY="-62" frameWidth="293" frameHeight="165"/>
	<SubTexture name="down0001" x="5" y="5" width="293" height="102" frameX="0" frameY="-62" frameWidth="293" frameHeight="165"/>
	<SubTexture name="down0002" x="303" y="5" width="227" height="161" frameX="-33" frameY="-4" frameWidth="293" frameHeight="165"/>
	<SubTexture name="down0003" x="303" y="5" width="227" height="161" frameX="-33" frameY="-4" frameWidth="293" frameHeight="165"/>
	<SubTexture name="down0004" x="535" y="5" width="223" height="163" frameX="-35" frameY="-2" frameWidth="293" frameHeight="165"/>
	<SubTexture name="down0005" x="535" y="5" width="223" height="163" frameX="-35" frameY="-2" frameWidth="293" frameHeight="165"/>
	<SubTexture name="down0006" x="763" y="5" width="219" height="165" frameX="-37" frameY="0" frameWidth="293" frameHeight="165"/>
	<SubTexture name="down0007" x="763" y="5" width="219" height="165" frameX="-37" frameY="0" frameWidth="293" frameHeight="165"/>
	<SubTexture name="idle0000" x="987" y="5" width="234" height="241" frameX="0" frameY="-47" frameWidth="234" frameHeight="288"/>
	<SubTexture name="idle0001" x="987" y="5" width="234" height="241" frameX="0" frameY="-47" frameWidth="234" frameHeight="288"/>
	<SubTexture name="idle0002" x="1226" y="5" width="190" height="280" frameX="-22" frameY="-8" frameWidth="234" frameHeight="288"/>
	<SubTexture name="idle0003" x="1226" y="5" width="190" height="280" frameX="-22" frameY="-8" frameWidth="234" frameHeight="288"/>
	<SubTexture name="idle0004" x="1421" y="5" width="181" height="286" frameX="-26" frameY="-2" frameWidth="234" frameHeight="288"/>
	<SubTexture name="idle0005" x="1421" y="5" width="181" height="286" frameX="-26" frameY="-2" frameWidth="234" frameHeight="288"/>
	<SubTexture name="idle0006" x="1607" y="5" width="177" height="288" frameX="-28" frameY="0" frameWidth="234" frameHeight="288"/>
	<SubTexture name="idle0007" x="1607" y="5" width="177" height="288" frameX="-28" frameY="0" frameWidth="234" frameHeight="288"/>
	<SubTexture name="idle0008" x="1607" y="5" width="177" height="288" frameX="-28" frameY="0" frameWidth="234" frameHeight="288"/>
	<SubTexture name="idle0009" x="1607" y="5" width="177" height="288" frameX="-28" frameY="0" frameWidth="234" frameHeight="288"/>
	<SubTexture name="left0000" x="5" y="298" width="340" height="254"/>
	<SubTexture name="left0001" x="5" y="298" width="340" height="254"/>
	<SubTexture name="left0002" x="350" y="298" width="304" height="254" frameX="-35" frameY="0" frameWidth="340" frameHeight="254"/>
	<SubTexture name="left0003" x="350" y="298" width="304" height="254" frameX="-35" frameY="0" frameWidth="340" frameHeight="254"/>
	<SubTexture name="left0004" x="659" y="298" width="298" height="254" frameX="-41" frameY="0" frameWidth="340" frameHeight="254"/>
	<SubTexture name="left0005" x="659" y="298" width="298" height="254" frameX="-41" frameY="0" frameWidth="340" frameHeight="254"/>
	<SubTexture name="left0006" x="962" y="298" width="296" height="254" frameX="-43" frameY="0" frameWidth="340" frameHeight="254"/>
	<SubTexture name="left0007" x="962" y="298" width="296" height="254" frameX="-43" frameY="0" frameWidth="340" frameHeight="254"/>
	<SubTexture name="right0000" x="1263" y="298" width="236" height="168"/>
	<SubTexture name="right0001" x="1263" y="298" width="236" height="168"/>
	<SubTexture name="right0002" x="1504" y="298" width="201" height="168" frameX="0" frameY="0" frameWidth="236" frameHeight="168"/>
	<SubTexture name="right0003" x="1504" y="298" width="201" height="168" frameX="0" frameY="0" frameWidth="236" frameHeight="168"/>
	<SubTexture name="right0004" x="1710" y="298" width="193" height="168" frameX="0" frameY="0" frameWidth="236" frameHeight="168"/>
	<SubTexture name="right0005" x="1710" y="298" width="193" height="168" frameX="0" frameY="0" frameWidth="236" frameHeight="168"/>
	<SubTexture name="right0006" x="5" y="557" width="188" height="168" frameX="0" frameY="0" frameWidth="236" frameHeight="168"/>
	<SubTexture name="right0007" x="5" y="557" width="188" height="168" frameX="0" frameY="0" frameWidth="236" frameHeight="168"/>
	<SubTexture name="up0000" x="198" y="557" width="140" height="317" frameX="-12" frameY="0" frameWidth="163" frameHeight="318"/>
	<SubTexture name="up0001" x="198" y="557" width="140" height="317" frameX="-12" frameY="0" frameWidth="163" frameHeight="318"/>
	<SubTexture name="up0002" x="343" y="557" width="151" height="302" frameX="-6" frameY="-15" frameWidth="163" frameHeight="318"/>
	<SubTexture name="up0003" x="343" y="557" width="151" height="302" frameX="-6" frameY="-15" frameWidth="163" frameHeight="318"/>
	<SubTexture name="up0004" x="499" y="557" width="157" height="297" frameX="-3" frameY="-20" frameWidth="163" frameHeight="318"/>
	<SubTexture name="up0005" x="499" y="557" width="157" height="297" frameX="-3" frameY="-20" frameWidth="163" frameHeight="318"/>
	<SubTexture name="up0006" x="661" y="557" width="163" height="296" frameX="0" frameY="-22" frameWidth="163" frameHeight="318"/>
	<SubTexture name="up0007" x="661" y="557" width="163" height="296" frameX="0" frameY="-22" frameWidth="163" frameHeight="318"/>
</TextureAtlas>
