{
	"animations": [
		{
			"loop": false,
			"offsets": [
				-90,
				0
			],
			"anim": "singLEFT",
			"fps": 24,
			"name": "left",
			"indices": []
		},
		{
			"loop": false,
			"offsets": [
				-120,
				-90
			],
			"anim": "singDOWN",
			"fps": 24,
			"name": "down",
			"indices": []
		},
		{
			"loop": false,
			"offsets": [
				-70,
				70
			],
			"anim": "singUP",
			"fps": 24,
			"name": "up",
			"indices": []
		},
		{
			"loop": false,
			"offsets": [
				-200,
				-20
			],
			"anim": "singRIGHT",
			"fps": 24,
			"name": "right",
			"indices": []
		},
		{
			"loop": true,
			"offsets": [
				0,
				0
			],
			"anim": "idle",
			"fps": 24,
			"name": "idle",
			"indices": []
		}
	],
	"no_antialiasing": true,
	"image": "bambi/chocolabi-crazy",
	"position": [
		0,
		0
	],
	"healthicon": "chocolabi-crazy",
	"flip_x": false,
	"healthbar_colors": [
		51,
		17,
		11
	],
	"camera_position": [
		0,
		0
	],
	"sing_duration": 6.1,
	"scale": 1
}